pysyge/__init__.py
pysyge/pysyge.py
pysyge-1.2.1.dist-info/AUTHORS
pysyge-1.2.1.dist-info/LICENSE
pysyge-1.2.1.dist-info/METADATA
pysyge-1.2.1.dist-info/WHEEL
pysyge-1.2.1.dist-info/top_level.txt
pysyge-1.2.1.dist-info/RECORD
